Metadata-Version: 2.4
Name: teachbooks
Version: 0.2.4
Summary: TeachBooks wrapper around JupyterBooks
Author-email: TeachBooks <teachbooks@tudelft.nl>
Project-URL: Homepage, https://github.com/teachbooks/teachbooks
Classifier: Programming Language :: Python :: 3
Requires-Python: >=3.10
License-File: LICENSE
Requires-Dist: jupyter-book~=1.0
Requires-Dist: click
Requires-Dist: psutil
Provides-Extra: testing
Requires-Dist: pytest; extra == "testing"
Requires-Dist: flaky; extra == "testing"
Provides-Extra: lint
Requires-Dist: ruff; extra == "lint"
Provides-Extra: docs
Requires-Dist: furo; extra == "docs"
Requires-Dist: numpydoc; extra == "docs"
Requires-Dist: sphinxcontrib-apidoc; extra == "docs"
Requires-Dist: sphinx-click; extra == "docs"
Provides-Extra: dev
Requires-Dist: teachbooks[docs,lint,testing]; extra == "dev"
Dynamic: license-file
